{"version":"3","listProblem":[{
  "tool": "Code Inspection",
  "category": "Code maturity",
  "type": "Call to 'printStackTrace()'",
  "severity": "High",
  "comment": "Call to 'printStackTrace()' should probably be replaced with more robust logging",
  "detailsInfo": "Reports calls to `Throwable.printStackTrace()` without arguments.\n\nSuch statements are often used for temporary debugging and should be either removed from the production code\nor replaced with a more robust logging facility.",
  "sources": [
    {
      "type": "file",
      "path": "app/src/main/java/com/qhy040404/libraryonetap/ui/about/ContributorViewBinder.java",
      "language": "JAVA",
      "line": 82,
      "offset": 23,
      "length": 15,
      "code": {
        "startLine": 80,
        "length": 15,
        "offset": 136,
        "surroundingCode": "                    v.getContext().startActivity(intent);\n                } catch (ActivityNotFoundException e) {\n                    e.printStackTrace();\n                }\n            }"
      }
    }
  ],
  "attributes": {
    "module": "图书馆.app.main",
    "inspectionName": "ThrowablePrintStackTrace"
  },
  "hash": "71aa254b68da65d7278fd90aee2be94ce94b32d9b874a31f28d11047db10945b"
},{
  "tool": "Code Inspection",
  "category": "Code maturity",
  "type": "Call to 'printStackTrace()'",
  "severity": "High",
  "comment": "Call to 'printStackTrace()' should probably be replaced with more robust logging",
  "detailsInfo": "Reports calls to `Throwable.printStackTrace()` without arguments.\n\nSuch statements are often used for temporary debugging and should be either removed from the production code\nor replaced with a more robust logging facility.",
  "sources": [
    {
      "type": "file",
      "path": "app/src/main/java/com/qhy040404/libraryonetap/recycleview/simplepage/ClickableItemViewBinder.java",
      "language": "JAVA",
      "line": 72,
      "offset": 23,
      "length": 15,
      "code": {
        "startLine": 70,
        "length": 15,
        "offset": 136,
        "surroundingCode": "                    v.getContext().startActivity(intent);\n                } catch (ActivityNotFoundException e) {\n                    e.printStackTrace();\n                }\n            }"
      }
    }
  ],
  "attributes": {
    "module": "图书馆.app.main",
    "inspectionName": "ThrowablePrintStackTrace"
  },
  "hash": "2592269c6e9d23ac47a697a8b54158a269763e534f163792f20f8d36823a141c"
},{
  "tool": "Code Inspection",
  "category": "Code maturity",
  "type": "Call to 'printStackTrace()'",
  "severity": "High",
  "comment": "Call to 'printStackTrace()' should probably be replaced with more robust logging",
  "detailsInfo": "Reports calls to `Throwable.printStackTrace()` without arguments.\n\nSuch statements are often used for temporary debugging and should be either removed from the production code\nor replaced with a more robust logging facility.",
  "sources": [
    {
      "type": "file",
      "path": "app/src/main/java/com/qhy040404/libraryonetap/recycleview/SimplePageActivity.java",
      "language": "JAVA",
      "line": 75,
      "offset": 19,
      "length": 15,
      "code": {
        "startLine": 73,
        "length": 15,
        "offset": 83,
        "surroundingCode": "                }\n            } catch (InterruptedException e) {\n                e.printStackTrace();\n            }\n        }"
      }
    }
  ],
  "attributes": {
    "module": "图书馆.app.main",
    "inspectionName": "ThrowablePrintStackTrace"
  },
  "hash": "1204c5bd341c31056685aa821f0f0c675bffa55536a3918940c8ff0f04c9f6ca"
}]}